pyplume/__init__.py
pyplume/ctd/__init__.py
pyplume/ctd/seabird_hex_decoder.py
pyplume/data_manager/data_manager.py
pyplume/data_visualizer/__init__.py
pyplume/data_visualizer/asset_templates.py
pyplume/data_visualizer/visualizer.py
pyplume/pd0/PT3.py
pyplume/pd0/__init__.py
pyplume/pd0/geometry.py
pyplume/pd0/masking.py
pyplume/pd0/pd0_decoder.py
pyplume/pd0/plotting.py
pyplume/pd0/processing.py
pyplume/plotting/__init__.py
pyplume/plotting/matplotlib_shell.py
pyplume/pose/Pose.py
pyplume/pose/__init__.py
pyplume/ptools/__init__.py
pyplume/ptools/ptools.py
pyplume_dhi-0.0.31.dist-info/METADATA
pyplume_dhi-0.0.31.dist-info/WHEEL
pyplume_dhi-0.0.31.dist-info/top_level.txt
pyplume_dhi-0.0.31.dist-info/RECORD
